_replicat_adapters.cpython-312-darwin.so
replicat/__version__.py
replicat/exceptions.py
replicat/repository.py
replicat/__main__.py
replicat/backends/local.py
replicat/backends/s3c.py
replicat/backends/b2.py
replicat/backends/s3.py
replicat/backends/base.py
replicat/tests/test_repository.py
replicat/tests/test_utils.py
replicat/tests/conftest.py
replicat/tests/__init__.py
replicat/tests/test_adapters.py
replicat/tests/test_local.py
replicat/utils/config.py
replicat/utils/compat.py
replicat/utils/__init__.py
replicat/utils/cli.py
replicat/utils/fs.py
replicat/utils/adapters.py
replicat-1.5.0.dist-info/RECORD
replicat-1.5.0.dist-info/LICENSE
replicat-1.5.0.dist-info/WHEEL
replicat-1.5.0.dist-info/entry_points.txt
replicat-1.5.0.dist-info/top_level.txt
replicat-1.5.0.dist-info/METADATA
