Metadata-Version: 2.2
Name: replicat
Version: 1.5.0
Summary: Configurable and lightweight backup utility with deduplication and encryption.
Home-page: https://github.com/vaultah/replicat
Maintainer: vaultah
Maintainer-email: flwaultah+replicat@gmail.com
Project-URL: Source, https://github.com/vaultah/replicat
Classifier: Development Status :: 5 - Production/Stable
Classifier: Environment :: Console
Classifier: Operating System :: MacOS :: MacOS X
Classifier: Operating System :: POSIX
Classifier: Operating System :: POSIX :: BSD
Classifier: Operating System :: POSIX :: Linux
Classifier: Operating System :: Microsoft :: Windows
Classifier: Programming Language :: Python
Classifier: Programming Language :: Python :: 3
Classifier: Programming Language :: Python :: 3 :: Only
Classifier: Programming Language :: Python :: 3.8
Classifier: Programming Language :: Python :: 3.9
Classifier: Programming Language :: Python :: 3.10
Classifier: Programming Language :: Python :: 3.11
Classifier: Programming Language :: Python :: 3.12
Classifier: Programming Language :: Python :: 3.13
Classifier: Topic :: System :: Archiving :: Backup
Classifier: License :: OSI Approved :: MIT License
Requires-Python: >=3.8
License-File: LICENSE
Requires-Dist: httpx<1,>=0.22
Requires-Dist: cryptography>=35
Requires-Dist: backoff<3,>=2
Requires-Dist: platformdirs<4.4,>=4.3.6
Requires-Dist: tqdm<5,>=4.63
Requires-Dist: sty<1.1,>=1
Requires-Dist: tomli>=1.1.0; python_version < "3.11"
Provides-Extra: test
Requires-Dist: pytest; extra == "test"
Requires-Dist: pytest-asyncio<0.17; extra == "test"
Provides-Extra: all
Requires-Dist: pytest; extra == "all"
Requires-Dist: pytest-asyncio<0.17; extra == "all"
Dynamic: classifier
Dynamic: description
Dynamic: description-content-type
Dynamic: home-page
Dynamic: maintainer
Dynamic: maintainer-email
Dynamic: project-url
Dynamic: provides-extra
Dynamic: requires-dist
Dynamic: requires-python
Dynamic: summary
